pybx/__init__.py
pybx/_modidx.py
pybx/anchor.py
pybx/basics.py
pybx/excepts.py
pybx/ops.py
pybx/sample.py
pybx/utils.py
pybx/vis.py
tests/__init__.py
tests/test_anchor.py
tests/test_basics.py
tests/test_ops.py
tests/test_sample.py
tests/test_vis.py
pybx-0.4.1.dist-info/LICENSE
pybx-0.4.1.dist-info/METADATA
pybx-0.4.1.dist-info/WHEEL
pybx-0.4.1.dist-info/entry_points.txt
pybx-0.4.1.dist-info/top_level.txt
pybx-0.4.1.dist-info/RECORD
