Metadata-Version: 2.1
Name: pybx
Version: 0.4.1
Summary: A simple python module to generate anchor boxes for object detection tasks.
Home-page: https://github.com/thatgeeman/pybx
Author: Geevarghese George
Author-email: thatgeeman@gmail.com
License: MIT License
Keywords: python computer-vision deep-learning fast-rcnn object-detection bounding-boxes rcnn multibox single-shot-multibox-detector single-shot-detection anchor-box rcnn-model multi-box single-shot-detector anchor-boxes multibox-detector
Classifier: Development Status :: 4 - Beta
Classifier: Intended Audience :: Developers
Classifier: Natural Language :: English
Classifier: Programming Language :: Python :: 3.7
Classifier: Programming Language :: Python :: 3.8
Classifier: Programming Language :: Python :: 3.9
Classifier: Programming Language :: Python :: 3.10
Classifier: License :: OSI Approved :: MIT License
Requires-Python: >=3.7
License-File: LICENSE
Requires-Dist: fastcore >=1.5.27
Requires-Dist: numpy ==1.21.6
Requires-Dist: matplotlib >=3.5
Requires-Dist: opencv-python ==4.7.0.72
Provides-Extra: dev
Requires-Dist: build ; extra == 'dev'
Requires-Dist: twine ; extra == 'dev'
Requires-Dist: ipykernel ; extra == 'dev'
Requires-Dist: pytest ; extra == 'dev'
Requires-Dist: python-build ; extra == 'dev'
Requires-Dist: nbdev ; extra == 'dev'
Requires-Dist: pre-commit ; extra == 'dev'
